{
	"info": {
		"_postman_id": "b5672f8e-5cb3-4eb2-b4a0-dffb92aba375",
		"name": "student",
		"schema": "https://schema.getpostman.com/json/collection/v2.1.0/collection.json"
	},
	"item": [
		{
			"name": "Add Student",
			"request": {
				"method": "POST",
				"header": [],
				"body": {
					"mode": "raw",
					"raw": "{\r\n  \"name\":\"shivanshi\",\r\n  \"email\":\"shivanshi22@gmail.com\",\r\n  \"age\":24,\r\n  \"rollnumber\":17056,\r\n  \"contact\":807760,\r\n  \"std\":6,\r\n  \"address\":\"225 patta\"\r\n}",
					"options": {
						"raw": {
							"language": "json"
						}
					}
				},
				"url": {
					"raw": "localhost:3000/student",
					"host": [
						"localhost"
					],
					"port": "3000",
					"path": [
						"student"
					]
				}
			},
			"response": []
		},
		{
			"name": "Get All Students",
			"request": {
				"method": "GET",
				"header": [],
				"url": {
					"raw": "localhost:3000/students",
					"host": [
						"localhost"
					],
					"port": "3000",
					"path": [
						"students"
					]
				}
			},
			"response": []
		},
		{
			"name": "Get Student By Id",
			"request": {
				"method": "GET",
				"header": [],
				"url": {
					"raw": "localhost:3000/student/id",
					"host": [
						"localhost"
					],
					"port": "3000",
					"path": [
						"student",
						"id"
					]
				}
			},
			"response": []
		},
		{
			"name": "Delete Student",
			"request": {
				"method": "DELETE",
				"header": [],
				"url": {
					"raw": "localhost:3000/student/60d07e41217b3f56bc63b9d8",
					"host": [
						"localhost"
					],
					"port": "3000",
					"path": [
						"student",
						"60d07e41217b3f56bc63b9d8"
					]
				}
			},
			"response": []
		},
		{
			"name": "Update Students",
			"request": {
				"method": "PATCH",
				"header": [],
				"body": {
					"mode": "raw",
					"raw": "{\r\n    \"name\":\"ayushkumar\"\r\n}",
					"options": {
						"raw": {
							"language": "json"
						}
					}
				},
				"url": {
					"raw": "localhost:3000/student/60d07e60217b3f56bc63b9d9",
					"host": [
						"localhost"
					],
					"port": "3000",
					"path": [
						"student",
						"60d07e60217b3f56bc63b9d9"
					]
				}
			},
			"response": []
		},
		{
			"name": "Sort Students",
			"request": {
				"method": "GET",
				"header": [],
				"url": {
					"raw": "localhost:3000/student/sort/key",
					"host": [
						"localhost"
					],
					"port": "3000",
					"path": [
						"student",
						"sort",
						"key"
					]
				}
			},
			"response": []
		}
	]
}